ctp/__init__.py
covid_tracking_project-0.2.dist-info/LICENSE
covid_tracking_project-0.2.dist-info/METADATA
covid_tracking_project-0.2.dist-info/WHEEL
covid_tracking_project-0.2.dist-info/top_level.txt
covid_tracking_project-0.2.dist-info/RECORD
