Metadata-Version: 2.1
Name: covid-tracking-project
Version: 0.2
Summary: A python wrapper for the Covid Tracking Project API
Home-page: https://github.com/gadhagod/covid-tracking-project
Author: Aarav Borthakur
Author-email: gadhaguy13@gmail.com
License: UNKNOWN
Platform: UNKNOWN
Classifier: Programming Language :: Python :: 3
Classifier: License :: OSI Approved :: MIT License
Classifier: Operating System :: OS Independent
Requires-Python: >=3.6
Requires-Dist: requests
